pyarcrbac/PyARCrbac.py
pyarcrbac/__init__.py
PyARCrbac-1.0.0.dist-info/LICENSE
PyARCrbac-1.0.0.dist-info/METADATA
PyARCrbac-1.0.0.dist-info/WHEEL
PyARCrbac-1.0.0.dist-info/top_level.txt
PyARCrbac-1.0.0.dist-info/RECORD
