Metadata-Version: 2.1
Name: PyARCrbac
Version: 1.0.0
Summary: A Library that simplifies interaction with Azure / ARC Metadata services.
Home-page: UNKNOWN
Author: ikbendion (dblonk)
Author-email: <contact@ikbendion.nl>
License: MIT
Project-URL: Source, https://github.com/ikbendion/PyARCrbac
Keywords: python,azure,rbac,azurearc,authentication,azmanagement
Platform: UNKNOWN
Classifier: Development Status :: 4 - Beta
Classifier: Intended Audience :: Developers
Classifier: Programming Language :: Python :: 3
Classifier: Operating System :: Unix
License-File: LICENSE
Requires-Dist: requests
